GoogleApiSupport/__init__.py
GoogleApiSupport/apis.py
GoogleApiSupport/auth.py
GoogleApiSupport/drive.py
GoogleApiSupport/sheets.py
GoogleApiSupport/slides.py
GoogleApiSupport/spreadsheets.py
GoogleApiSupport/storage.py
test/__init__.py
test/test_spreadsheets.py
google_api_support-0.1.8.dist-info/LICENSE.md
google_api_support-0.1.8.dist-info/METADATA
google_api_support-0.1.8.dist-info/WHEEL
google_api_support-0.1.8.dist-info/top_level.txt
google_api_support-0.1.8.dist-info/RECORD
