Metadata-Version: 2.1
Name: google-api-support
Version: 0.1.8
Summary: In this package you will find functions to deal with google apis. Sheets, Drive, Storage and Slides
Home-page: https://github.com/vperezb/google-api-support
Author: Víctor Pérez Berruezo
Author-email: vperezb@proton.me
Classifier: Programming Language :: Python :: 3
Classifier: License :: Public Domain
Classifier: Development Status :: 3 - Alpha
License-File: LICENSE.md
Requires-Dist: google-api-python-client
Requires-Dist: httplib2
Requires-Dist: oauth2client
Requires-Dist: pandas
Requires-Dist: google-cloud-storage
Requires-Dist: google-auth
Requires-Dist: google-auth-oauthlib
